exdec/__init__.py
exdec/data_classes.py
exdec/decorator.py
exdec/manager.py
exdec/utils.py
exdec-1.0.2.dist-info/LICENSE
exdec-1.0.2.dist-info/METADATA
exdec-1.0.2.dist-info/WHEEL
exdec-1.0.2.dist-info/top_level.txt
exdec-1.0.2.dist-info/RECORD
