Metadata-Version: 2.1
Name: exdec
Version: 1.0.2
Summary: Decorator for catching exceptions in functions and methods.
Home-page: https://github.com/EvgeniyBurdin/exdec
Author: Evgeniy Burdin
Author-email: e.s.burdin@gmail.com
License: MIT
Keywords: decorator function method exception try except
Platform: UNKNOWN
Classifier: Programming Language :: Python :: 3.7
Classifier: Programming Language :: Python :: 3.8
Classifier: Programming Language :: Python :: 3.9
Classifier: Programming Language :: Python :: 3.10
Classifier: License :: OSI Approved :: BSD License
Classifier: Operating System :: OS Independent
Classifier: Topic :: Software Development
Requires-Python: >=3.7
